bn_modeller/__init__.py
bn_modeller/app.py
bn_modeller/bayesian_nets/__init__.py
bn_modeller/bayesian_nets/correlations.py
bn_modeller/bayesian_nets/graph_preparation.py
bn_modeller/bayesian_nets/pyBansheeCalculation.py
bn_modeller/bayesian_nets/utils.py
bn_modeller/button_page.py
bn_modeller/dialogs/__init__.py
bn_modeller/dialogs/about_dialog.py
bn_modeller/input_output.py
bn_modeller/jointgrid.py
bn_modeller/link_table.py
bn_modeller/main.py
bn_modeller/models/__init__.py
bn_modeller/models/checkable_sort_filter_proxy_model.py
bn_modeller/models/dependency_sqltable_model.py
bn_modeller/models/feature_sqltable_model.py
bn_modeller/models/relational_sort_filter_proxy_model.py
bn_modeller/models/sample_sqltable_model.py
bn_modeller/resources/icon.ico
bn_modeller/resources/templates/datasource_cols.csv
bn_modeller/resources/templates/datasource_cols.xlsx
bn_modeller/resources/templates/datasource_rows.csv
bn_modeller/resources/templates/datasource_rows.xlsx
bn_modeller/utils/__init__.py
bn_modeller/utils/db_model_handler.py
bn_modeller/utils/model_adapters.py
bn_modeller/widgets/__init__.py
bn_modeller/widgets/all_samples_view.py
bn_modeller/widgets/bn_visualization_view.py
bn_modeller/widgets/dep_setup_table_view.py
bn_modeller/widgets/extended_slider_widget.py
bn_modeller/widgets/file_path_widget.py
bn_modeller/widgets/page/bayesian_network_page.py
bn_modeller/widgets/page/database_page.py
bn_modeller/widgets/page/regr_plot_page.py
bn_modeller/widgets/plots/__init__.py
bn_modeller/widgets/plots/pairplot_view.py
bn_modeller/widgets/project_wizard.py
bn_modeller/widgets/selectable_list_view.py
bn_modeller/widgets/separator_widget.py
bn_modeller/widgets/vertical_label.py
bn_modeller/windows/__init__.py
bn_modeller/windows/base_window.py
bn_modeller/windows/main_window.py
bn_modeller-1.0.0.dist-info/LICENSE
bn_modeller-1.0.0.dist-info/METADATA
bn_modeller-1.0.0.dist-info/WHEEL
bn_modeller-1.0.0.dist-info/entry_points.txt
bn_modeller-1.0.0.dist-info/RECORD
