Metadata-Version: 2.3
Name: bn_modeller
Version: 1.0.0
Summary: A program to represents a set of variables and their conditional dependencies via a directed acyclic graph.
License: GPL-3.0-or-later
Author: Aleksandr Sinitca
Author-email: amsinitca@etu.ru
Requires-Python: >=3.10,<3.14
Classifier: License :: OSI Approved :: GNU General Public License v3 or later (GPLv3+)
Classifier: Programming Language :: Python :: 3
Classifier: Programming Language :: Python :: 3.10
Classifier: Programming Language :: Python :: 3.11
Classifier: Programming Language :: Python :: 3.12
Classifier: Programming Language :: Python :: 3.13
Requires-Dist: openpyxl (>=3.1.5,<4.0.0)
Requires-Dist: pingouin (>=0.5.5,<0.6.0)
Requires-Dist: py-banshee (>=1.1.2,<2.0.0)
Requires-Dist: pygraphviz (>=1.14,<2.0)
Requires-Dist: pyside6 (>=6.8.1.1,<7.0.0.0)
